napari_power_spectrum/__init__.py
napari_power_spectrum/_widget.py
napari_power_spectrum/napari.yaml
napari_power_spectrum/_tests/__init__.py
napari_power_spectrum/_tests/test_widget.py
napari_power_spectrum-0.0.6.dist-info/LICENSE
napari_power_spectrum-0.0.6.dist-info/METADATA
napari_power_spectrum-0.0.6.dist-info/WHEEL
napari_power_spectrum-0.0.6.dist-info/entry_points.txt
napari_power_spectrum-0.0.6.dist-info/top_level.txt
napari_power_spectrum-0.0.6.dist-info/RECORD
