Metadata-Version: 2.1
Name: napari-power-spectrum
Version: 0.0.6
Summary: A simple plugin to get the power spectrum of frames of a stack image
Home-page: https://github.com/GiorgiaTortora/napari-power-spectrum
Author: Giorgia Tortora
Author-email: giorgiatortora2@gmail.com
License: BSD-3-Clause
Project-URL: Bug Tracker, https://github.com/GiorgiaTortora/napari-power-spectrum/issues
Project-URL: Documentation, https://github.com/GiorgiaTortora/napari-power-spectrum#README.md
Project-URL: Source Code, https://github.com/GiorgiaTortora/napari-power-spectrum
Project-URL: User Support, https://github.com/GiorgiaTortora/napari-power-spectrum/issues
Platform: UNKNOWN
Classifier: Development Status :: 2 - Pre-Alpha
Classifier: Intended Audience :: Developers
Classifier: Framework :: napari
Classifier: Topic :: Software Development :: Testing
Classifier: Programming Language :: Python
Classifier: Programming Language :: Python :: 3
Classifier: Programming Language :: Python :: 3.8
Classifier: Programming Language :: Python :: 3.9
Classifier: Programming Language :: Python :: 3.10
Classifier: Operating System :: OS Independent
Classifier: License :: OSI Approved :: BSD License
Requires-Python: >=3.8
License-File: LICENSE
Requires-Dist: numpy
Requires-Dist: magicgui
Requires-Dist: qtpy
Provides-Extra: testing
Requires-Dist: tox ; extra == 'testing'
Requires-Dist: pytest ; extra == 'testing'
Requires-Dist: pytest-cov ; extra == 'testing'
Requires-Dist: pytest-qt ; extra == 'testing'
Requires-Dist: napari ; extra == 'testing'
Requires-Dist: pyqt5 ; extra == 'testing'
